wserver_compound/__init__.py
wserver_compound/functions.py
wserver_compound/main.py
wserver_compound/methods.py
wserver_compound/settings.py
wserver_compound/tests/__init__.py
wserver_compound/tests/api_test.py
wserver_compound/tests/functions_test.py
wserver_compound/tests/main_test.py
wserver_compound/tests/methods_tests.py
wserver_compound/tests/test_objects.py
wserver_compound-0.0.2.dist-info/METADATA
wserver_compound-0.0.2.dist-info/WHEEL
wserver_compound-0.0.2.dist-info/top_level.txt
wserver_compound-0.0.2.dist-info/RECORD
