Metadata-Version: 2.1
Name: wserver-compound
Version: 0.0.2
Summary: UNKNOWN
Home-page: UNKNOWN
Author: PunchyArchy
Author-email: ksmdrmvscthny@gmail.com
License: UNKNOWN
Platform: UNKNOWN
Requires-Dist: qodex-pi
Requires-Dist: wsqluse
Requires-Dist: gc-qdk
Requires-Dist: wta
